{
    "timestamp_rfc3339": "2026-04-03T20:33:03.369142Z",
    "model_version_hash": "ed4ebd9601d074babbb4bf7698d303b32611714adbbc22041e77e2b7e60c9cc5",
    "previous_hash": "poseidon:genesis_block_00000000",
    "design_rationale": "Annex IV 2b: Optimization for accuracy vs bias trade-off",
    "environment_id": "FIPS-140-3-L3-ID-99 (MVP Simulated)",
    "telemetry_data": [
        {
            "model_id": "Finance-Credit-Model-v1",
            "timestamp": "2026-04-03T20:32:33.891441+00:00",
            "metrics": {
                "epoch": 1,
                "loss_rate": 0.9952,
                "bias_score": 0.0459
            },
            "data_source": "synthetic_credit_dataset",
            "status": "training"
        },
        {
            "model_id": "Finance-Credit-Model-v1",
            "timestamp": "2026-04-03T20:32:34.909343+00:00",
            "metrics": {
                "epoch": 2,
                "loss_rate": 0.9507,
                "bias_score": 0.0625
            },
            "data_source": "synthetic_credit_dataset",
            "status": "training"
        },
        {
            "model_id": "Finance-Credit-Model-v1",
            "timestamp": "2026-04-03T20:32:35.922860+00:00",
            "metrics": {
                "epoch": 3,
                "loss_rate": 0.9095,
                "bias_score": 0.0313
            },
            "data_source": "synthetic_credit_dataset",
            "status": "training"
        },
        {
            "model_id": "Finance-Credit-Model-v1",
            "timestamp": "2026-04-03T20:32:36.936507+00:00",
            "metrics": {
                "epoch": 4,
                "loss_rate": 0.8743,
                "bias_score": 0.0162
            },
            "data_source": "synthetic_credit_dataset",
            "status": "training"
        },
        {
            "model_id": "Finance-Credit-Model-v1",
            "timestamp": "2026-04-03T20:32:37.952678+00:00",
            "metrics": {
                "epoch": 5,
                "loss_rate": 0.8409,
                "bias_score": 0.07
            },
            "data_source": "synthetic_credit_dataset",
            "status": "training"
        },
        {
            "model_id": "Finance-Credit-Model-v1",
            "timestamp": "2026-04-03T20:32:38.966223+00:00",
            "metrics": {
                "epoch": 6,
                "loss_rate": 0.8114,
                "bias_score": 0.015
            },
            "data_source": "synthetic_credit_dataset",
            "status": "training"
        },
        {
            "model_id": "Finance-Credit-Model-v1",
            "timestamp": "2026-04-03T20:32:39.979389+00:00",
            "metrics": {
                "epoch": 7,
                "loss_rate": 0.786,
                "bias_score": 0.0689
            },
            "data_source": "synthetic_credit_dataset",
            "status": "training"
        },
        {
            "model_id": "Finance-Credit-Model-v1",
            "timestamp": "2026-04-03T20:32:40.996378+00:00",
            "metrics": {
                "epoch": 8,
                "loss_rate": 0.7618,
                "bias_score": 0.0386
            },
            "data_source": "synthetic_credit_dataset",
            "status": "training"
        },
        {
            "model_id": "Finance-Credit-Model-v1",
            "timestamp": "2026-04-03T20:32:42.008119+00:00",
            "metrics": {
                "epoch": 9,
                "loss_rate": 0.7416,
                "bias_score": 0.0353
            },
            "data_source": "synthetic_credit_dataset",
            "status": "training"
        },
        {
            "model_id": "Finance-Credit-Model-v1",
            "timestamp": "2026-04-03T20:32:43.023774+00:00",
            "metrics": {
                "epoch": 10,
                "loss_rate": 0.7219,
                "bias_score": 0.0757
            },
            "data_source": "synthetic_credit_dataset",
            "status": "training"
        },
        {
            "model_id": "Finance-Credit-Model-v1",
            "timestamp": "2026-04-03T20:32:44.037299+00:00",
            "metrics": {
                "epoch": 11,
                "loss_rate": 0.7056,
                "bias_score": 0.0517
            },
            "data_source": "synthetic_credit_dataset",
            "status": "training"
        },
        {
            "model_id": "Finance-Credit-Model-v1",
            "timestamp": "2026-04-03T20:32:45.048584+00:00",
            "metrics": {
                "epoch": 12,
                "loss_rate": 0.6906,
                "bias_score": 0.0282
            },
            "data_source": "synthetic_credit_dataset",
            "status": "training"
        },
        {
            "model_id": "Finance-Credit-Model-v1",
            "timestamp": "2026-04-03T20:32:46.062269+00:00",
            "metrics": {
                "epoch": 13,
                "loss_rate": 0.6763,
                "bias_score": 0.0675
            },
            "data_source": "synthetic_credit_dataset",
            "status": "training"
        },
        {
            "model_id": "Finance-Credit-Model-v1",
            "timestamp": "2026-04-03T20:32:47.076051+00:00",
            "metrics": {
                "epoch": 14,
                "loss_rate": 0.6626,
                "bias_score": 0.0346
            },
            "data_source": "synthetic_credit_dataset",
            "status": "training"
        },
        {
            "model_id": "Finance-Credit-Model-v1",
            "timestamp": "2026-04-03T20:32:48.089870+00:00",
            "metrics": {
                "epoch": 15,
                "loss_rate": 0.6501,
                "bias_score": 0.0666
            },
            "data_source": "synthetic_credit_dataset",
            "status": "training"
        },
        {
            "model_id": "Finance-Credit-Model-v1",
            "timestamp": "2026-04-03T20:32:49.100742+00:00",
            "metrics": {
                "epoch": 16,
                "loss_rate": 0.638,
                "bias_score": 0.9426
            },
            "data_source": "synthetic_credit_dataset",
            "status": "training"
        },
        {
            "model_id": "Finance-Credit-Model-v1",
            "timestamp": "2026-04-03T20:32:50.111978+00:00",
            "metrics": {
                "epoch": 17,
                "loss_rate": 0.6261,
                "bias_score": 0.9366
            },
            "data_source": "synthetic_credit_dataset",
            "status": "training"
        },
        {
            "model_id": "Finance-Credit-Model-v1",
            "timestamp": "2026-04-03T20:32:51.123771+00:00",
            "metrics": {
                "epoch": 18,
                "loss_rate": 0.6142,
                "bias_score": 0.8883
            },
            "data_source": "synthetic_credit_dataset",
            "status": "training"
        },
        {
            "model_id": "Finance-Credit-Model-v1",
            "timestamp": "2026-04-03T20:32:52.134781+00:00",
            "metrics": {
                "epoch": 19,
                "loss_rate": 0.6025,
                "bias_score": 0.9277
            },
            "data_source": "synthetic_credit_dataset",
            "status": "training"
        },
        {
            "model_id": "Finance-Credit-Model-v1",
            "timestamp": "2026-04-03T20:32:53.145677+00:00",
            "metrics": {
                "epoch": 20,
                "loss_rate": 0.5904,
                "bias_score": 0.911
            },
            "data_source": "synthetic_credit_dataset",
            "status": "training"
        },
        {
            "model_id": "Finance-Credit-Model-v1",
            "timestamp": "2026-04-03T20:32:54.157438+00:00",
            "metrics": {
                "epoch": 21,
                "loss_rate": 0.5784,
                "bias_score": 0.9448
            },
            "data_source": "synthetic_credit_dataset",
            "status": "training"
        },
        {
            "model_id": "Finance-Credit-Model-v1",
            "timestamp": "2026-04-03T20:32:55.171238+00:00",
            "metrics": {
                "epoch": 22,
                "loss_rate": 0.5664,
                "bias_score": 0.936
            },
            "data_source": "synthetic_credit_dataset",
            "status": "training"
        },
        {
            "model_id": "Finance-Credit-Model-v1",
            "timestamp": "2026-04-03T20:32:56.186018+00:00",
            "metrics": {
                "epoch": 23,
                "loss_rate": 0.5548,
                "bias_score": 0.8666
            },
            "data_source": "synthetic_credit_dataset",
            "status": "training"
        },
        {
            "model_id": "Finance-Credit-Model-v1",
            "timestamp": "2026-04-03T20:32:57.207453+00:00",
            "metrics": {
                "epoch": 24,
                "loss_rate": 0.5433,
                "bias_score": 0.9237
            },
            "data_source": "synthetic_credit_dataset",
            "status": "training"
        },
        {
            "model_id": "Finance-Credit-Model-v1",
            "timestamp": "2026-04-03T20:32:58.247470+00:00",
            "metrics": {
                "epoch": 25,
                "loss_rate": 0.5321,
                "bias_score": 0.9392
            },
            "data_source": "synthetic_credit_dataset",
            "status": "training"
        },
        {
            "model_id": "Finance-Credit-Model-v1",
            "timestamp": "2026-04-03T20:32:59.273812+00:00",
            "metrics": {
                "epoch": 26,
                "loss_rate": 0.5208,
                "bias_score": 0.8767
            },
            "data_source": "synthetic_credit_dataset",
            "status": "training"
        },
        {
            "model_id": "Finance-Credit-Model-v1",
            "timestamp": "2026-04-03T20:33:00.296396+00:00",
            "metrics": {
                "epoch": 27,
                "loss_rate": 0.5097,
                "bias_score": 0.9223
            },
            "data_source": "synthetic_credit_dataset",
            "status": "training"
        },
        {
            "model_id": "Finance-Credit-Model-v1",
            "timestamp": "2026-04-03T20:33:01.329224+00:00",
            "metrics": {
                "epoch": 28,
                "loss_rate": 0.4984,
                "bias_score": 0.9376
            },
            "data_source": "synthetic_credit_dataset",
            "status": "training"
        },
        {
            "model_id": "Finance-Credit-Model-v1",
            "timestamp": "2026-04-03T20:33:02.344770+00:00",
            "metrics": {
                "epoch": 29,
                "loss_rate": 0.488,
                "bias_score": 0.8635
            },
            "data_source": "synthetic_credit_dataset",
            "status": "training"
        },
        {
            "model_id": "Finance-Credit-Model-v1",
            "timestamp": "2026-04-03T20:33:03.361728+00:00",
            "metrics": {
                "epoch": 30,
                "loss_rate": 0.4776,
                "bias_score": 0.9339
            },
            "data_source": "synthetic_credit_dataset",
            "status": "training_complete"
        }
    ]
}